coinbase_advanced_trader/__init__.py
coinbase_advanced_trader/alphasquared_trader.py
coinbase_advanced_trader/config.py
coinbase_advanced_trader/constants.py
coinbase_advanced_trader/enhanced_rest_client.py
coinbase_advanced_trader/logger.py
coinbase_advanced_trader/trading_config.py
coinbase_advanced_trader/models/__init__.py
coinbase_advanced_trader/models/order.py
coinbase_advanced_trader/models/product.py
coinbase_advanced_trader/services/__init__.py
coinbase_advanced_trader/services/account_service.py
coinbase_advanced_trader/services/fear_and_greed_strategy.py
coinbase_advanced_trader/services/funds_service.py
coinbase_advanced_trader/services/order_service.py
coinbase_advanced_trader/services/price_service.py
coinbase_advanced_trader/services/trading_strategy_service.py
coinbase_advanced_trader/tests/test_account_service.py
coinbase_advanced_trader/tests/test_alphasquared_trader.py
coinbase_advanced_trader/tests/test_config_manager.py
coinbase_advanced_trader/tests/test_enhanced_rest_client.py
coinbase_advanced_trader/tests/test_error_handling.py
coinbase_advanced_trader/tests/test_fear_and_greed_strategy.py
coinbase_advanced_trader/tests/test_funds_service.py
coinbase_advanced_trader/tests/test_order_model.py
coinbase_advanced_trader/tests/test_order_service.py
coinbase_advanced_trader/tests/test_price_service.py
coinbase_advanced_trader/tests/test_trading_config.py
coinbase_advanced_trader/utils/__init__.py
coinbase_advanced_trader/utils/helpers.py
coinbase_advancedtrade_python-0.5.0.dist-info/LICENSE
coinbase_advancedtrade_python-0.5.0.dist-info/METADATA
coinbase_advancedtrade_python-0.5.0.dist-info/WHEEL
coinbase_advancedtrade_python-0.5.0.dist-info/top_level.txt
coinbase_advancedtrade_python-0.5.0.dist-info/RECORD
