Metadata-Version: 2.2
Name: coinbase-advancedtrade-python
Version: 0.5.0
Summary: The unofficial Python client for the Coinbase Advanced Trade API
Home-page: https://github.com/rhettre/coinbase-advancedtrade-python
Author: Rhett Reisman
Author-email: rhett@rhett.blog
License: MIT
Keywords: gdax,gdax-api,cbpro,cbpro-api,orderbook,trade,bitcoin,ethereum,BTC,ETH,client,api,wrapper,exchange,crypto,currency,trading,trading-api,coinbase,advanced-trade,prime,coinbaseadvancedtrade,coinbase-advanced-trade,fear-and-greed-index
Classifier: Development Status :: 3 - Alpha
Classifier: Intended Audience :: Developers
Classifier: Intended Audience :: Financial and Insurance Industry
Classifier: Intended Audience :: Information Technology
Classifier: Topic :: Software Development :: Libraries :: Python Modules
Classifier: License :: OSI Approved :: MIT License
Classifier: Programming Language :: Python :: 3
Classifier: Programming Language :: Python :: 3.12
Requires-Python: >=3.12
License-File: LICENSE
Requires-Dist: coinbase-advanced-py==1.8.2
Requires-Dist: requests>=2.31.0
Requires-Dist: urllib3>=2.2.2
Requires-Dist: PyYAML>=6.0.1
Requires-Dist: cryptography>=42.0.4
Requires-Dist: cffi
Requires-Dist: alphasquared-py>=0.3.0
Requires-Dist: fear-and-greed-crypto>=0.1.0
Dynamic: author
Dynamic: author-email
Dynamic: classifier
Dynamic: description
Dynamic: description-content-type
Dynamic: home-page
Dynamic: keywords
Dynamic: license
Dynamic: requires-dist
Dynamic: requires-python
Dynamic: summary
